printrevolution/__init__.py
printrevolution-0.1.1.dist-info/entry_points.txt
printrevolution-0.1.1.dist-info/WHEEL
printrevolution-0.1.1.dist-info/METADATA
printrevolution-0.1.1.dist-info/RECORD
