Metadata-Version: 2.1
Name: printrevolution
Version: 0.1.1
Summary: A soothing meditation on politics.
Author: Sam Lavigne
Author-email: splavigne@gmail.com
Requires-Python: >=3.7,<4.0
Classifier: Programming Language :: Python :: 3
Classifier: Programming Language :: Python :: 3.10
Classifier: Programming Language :: Python :: 3.7
Classifier: Programming Language :: Python :: 3.8
Classifier: Programming Language :: Python :: 3.9
